hdfs_kerberos_no_verify/__init__.py
hdfs_kerberos_no_verify/kerberos_no_verify.py
hdfs_kerberos_no_verify-0.0.1.dist-info/METADATA
hdfs_kerberos_no_verify-0.0.1.dist-info/WHEEL
hdfs_kerberos_no_verify-0.0.1.dist-info/top_level.txt
hdfs_kerberos_no_verify-0.0.1.dist-info/RECORD
