Metadata-Version: 2.1
Name: hdfs-kerberos-no-verify
Version: 0.0.1
Summary: A custom of from hdfs.ext.kerberos import KerberosClient from hdfs package that allow you to use with self-signed https url.
Author-email: Thai Thien <thien.thai.meow@gmail.com>
Project-URL: Homepage, https://github.com/ttpro1995/hdfs-kerberos-no-verify
Project-URL: Bug Tracker, https://github.com/ttpro1995/hdfs-kerberos-no-verify/issues
Classifier: Programming Language :: Python :: 3.8 
Classifier: Programming Language :: Python :: 3.9
Classifier: Programming Language :: Python :: 3.10
Classifier: License :: OSI Approved :: MIT License
Classifier: Development Status :: 1 - Planning
Classifier: Intended Audience :: Developers
Classifier: Operating System :: OS Independent
Requires-Python: >=3.8
Requires-Dist: hdfs[kerberos] >=2.7
